Metadata-Version: 2.1
Name: mutacc
Version: 1.7.2
Summary: The mutation accumulation database
Home-page: https://github.com/Clinical-Genomics/mutacc
Author: Adam Rosenbaum
Author-email: adam.rosenbaum@scilifelab.se
License: MIT
Classifier: License :: OSI Approved :: MIT License
Classifier: Programming Language :: Python :: 3.8
Classifier: Environment :: Console
Requires-Python: >=3.6.0
License-File: LICENSE
Requires-Dist: Click
Requires-Dist: pysam
Requires-Dist: coloredlogs
Requires-Dist: biopython
Requires-Dist: cyvcf2
Requires-Dist: importlib-resources
Requires-Dist: mongo-adapter >=0.3.3
Requires-Dist: ped-parser
Requires-Dist: PyYaml >=5.1
Requires-Dist: pymongo
